[
  {
    "현행연혁코드": "현행",
    "법령일련번호": "246621",
    "자법타법여부": "",
    "법령상세링크": "/DRF/lawService.do?OC=lee&target=law&MST=246621&type=HTML&mobileYn=&efYd=20221227",
    "법령명한글": "5ㆍ18민주화운동 관련자 보상 등에 관한 법률",
    "법령구분명": "법률",
    "소관부처명": "행정안전부",
    "공포번호": "19106",
    "제개정구분명": "일부개정",
    "소관부처코드": "1741000",
    "id": "1",
    "법령ID": "001234",
    "공동부령정보": "",
    "시행일자": "20221227",
    "공포일자": "20221227",
    "법령약칭명": "5ㆍ18보상법"
  },
  {
    "현행연혁코드": "현행",
    "법령일련번호": "266347",
    "자법타법여부": "",
    "법령상세링크": "/DRF/lawService.do?OC=lee&target=law&MST=266347&type=HTML&mobileYn=&efYd=20241112",
    "법령명한글": "5ㆍ18민주화운동 관련자 보상 등에 관한 법률 시행령",
    "법령구분명": "대통령령",
    "소관부처명": "행정안전부",
    "공포번호": "34989",
    "제개정구분명": "타법개정",
    "소관부처코드": "1741000",
    "id": "2",
    "법령ID": "002543",
    "공동부령정보": "",
    "시행일자": "20241112",
    "공포일자": "20241112",
    "법령약칭명": "5ㆍ18보상법 시행령"
  },
  {
    "현행연혁코드": "현행",
    "법령일련번호": "266675",
    "자법타법여부": "",
    "법령상세링크": "/DRF/lawService.do?OC=lee&target=law&MST=266675&type=HTML&mobileYn=&efYd=20250401",
    "법령명한글": "6ㆍ25전쟁 전후 적 지역에서 활동한 비정규군 공로자 보상에 관한 법률",
    "법령구분명": "법률",
    "소관부처명": "국방부",
    "공포번호": "20536",
    "제개정구분명": "일부개정",
    "소관부처코드": "1290000",
    "id": "3",
    "법령ID": "014062",
    "공동부령정보": "",
    "시행일자": "20250401",
    "공포일자": "20241203",
    "법령약칭명": "6ㆍ25비정규군보상법"
  },
  {
    "현행연혁코드": "현행",
    "법령일련번호": "266349",
    "자법타법여부": "",
    "법령상세링크": "/DRF/lawService.do?OC=lee&target=law&MST=266349&type=HTML&mobileYn=&efYd=20241112",
    "법령명한글": "6ㆍ25전쟁 전후 적 지역에서 활동한 비정규군 공로자 보상에 관한 법률 시행령",
    "법령구분명": "대통령령",
    "소관부처명": "국방부",
    "공포번호": "34989",
    "제개정구분명": "타법개정",
    "소관부처코드": "1290000",
    "id": "4",
    "법령ID": "014166",
    "공동부령정보": "",
    "시행일자": "20241112",
    "공포일자": "20241112",
    "법령약칭명": "6ㆍ25비정규군보상법 시행령"
  },
  {
    "현행연혁코드": "현행",
    "법령일련번호": "183520",
    "자법타법여부": "",
    "법령상세링크": "/DRF/lawService.do?OC=lee&target=law&MST=183520&type=HTML&mobileYn=&efYd=20161130",
    "법령명한글": "경비교도대 폐지에 따른 보상 등에 관한 법률",
    "법령구분명": "법률",
    "소관부처명": "법무부",
    "공포번호": "14170",
    "제개정구분명": "제정",
    "소관부처코드": "1270000",
    "id": "5",
    "법령ID": "012557",
    "공동부령정보": "",
    "시행일자": "20161130",
    "공포일자": "20160529",
    "법령약칭명": "경비교도대보상법"
  },
  {
    "현행연혁코드": "현행",
    "법령일련번호": "261779",
    "자법타법여부": "",
    "법령상세링크": "/DRF/lawService.do?OC=lee&target=law&MST=261779&type=HTML&mobileYn=&efYd=20240416",
    "법령명한글": "경비교도대 폐지에 따른 보상 등에 관한 법률 시행령",
    "법령구분명": "대통령령",
    "소관부처명": "법무부",
    "공포번호": "34407",
    "제개정구분명": "일부개정",
    "소관부처코드": "1270000",
    "id": "6",
    "법령ID": "012676",
    "공동부령정보": "",
    "시행일자": "20240416",
    "공포일자": "20240416",
    "법령약칭명": "경비교도대보상법 시행령"
  },
  {
    "현행연혁코드": "현행",
    "법령일련번호": "265491",
    "자법타법여부": "",
    "법령상세링크": "/DRF/lawService.do?OC=lee&target=law&MST=265491&type=HTML&mobileYn=&efYd=20240920",
    "법령명한글": "공익사업을 위한 토지 등의 취득 및 보상에 관한 법률",
    "법령구분명": "법률",
    "소관부처명": "국토교통부",
    "공포번호": "20452",
    "제개정구분명": "일부개정",
    "소관부처코드": "1613000",
    "id": "7",
    "법령ID": "009295",
    "공동부령정보": "",
    "시행일자": "20240920",
    "공포일자": "20240920",
    "법령약칭명": "토지보상법"
  },
  {
    "현행연혁코드": "현행",
    "법령일련번호": "261719",
    "자법타법여부": "",
    "법령상세링크": "/DRF/lawService.do?OC=lee&target=law&MST=261719&type=HTML&mobileYn=&efYd=20240409",
    "법령명한글": "공익사업을 위한 토지 등의 취득 및 보상에 관한 법률 시행령",
    "법령구분명": "대통령령",
    "소관부처명": "국토교통부",
    "공포번호": "34400",
    "제개정구분명": "일부개정",
    "소관부처코드": "1613000",
    "id": "8",
    "법령ID": "009451",
    "공동부령정보": "",
    "시행일자": "20240409",
    "공포일자": "20240409",
    "법령약칭명": "토지보상법 시행령"
  },
  {
    "현행연혁코드": "현행",
    "법령일련번호": "261727",
    "자법타법여부": "",
    "법령상세링크": "/DRF/lawService.do?OC=lee&target=law&MST=261727&type=HTML&mobileYn=&efYd=20240409",
    "법령명한글": "공익사업을 위한 토지 등의 취득 및 보상에 관한 법률 시행규칙",
    "법령구분명": "국토교통부령",
    "소관부처명": "국토교통부",
    "공포번호": "01322",
    "제개정구분명": "일부개정",
    "소관부처코드": "1613000",
    "id": "9",
    "법령ID": "009471",
    "공동부령정보": "",
    "시행일자": "20240409",
    "공포일자": "20240409",
    "법령약칭명": "토지보상법 시행규칙"
  },
  {
    "현행연혁코드": "현행",
    "법령일련번호": "211459",
    "자법타법여부": "",
    "법령상세링크": "/DRF/lawService.do?OC=lee&target=law&MST=211459&type=HTML&mobileYn=&efYd=20201127",
    "법령명한글": "군용비행장ㆍ군사격장 소음 방지 및 피해 보상에 관한 법률",
    "법령구분명": "법률",
    "소관부처명": "국방부",
    "공포번호": "16582",
    "제개정구분명": "제정",
    "소관부처코드": "1290000",
    "id": "10",
    "법령ID": "013608",
    "공동부령정보": "",
    "시행일자": "20201127",
    "공포일자": "20191126",
    "법령약칭명": "군소음보상법"
  },
  {
    "현행연혁코드": "현행",
    "법령일련번호": "266529",
    "자법타법여부": "",
    "법령상세링크": "/DRF/lawService.do?OC=lee&target=law&MST=266529&type=HTML&mobileYn=&efYd=20250101",
    "법령명한글": "군용비행장ㆍ군사격장 소음 방지 및 피해 보상에 관한 법률 시행령",
    "법령구분명": "대통령령",
    "소관부처명": "국방부",
    "공포번호": "35009",
    "제개정구분명": "일부개정",
    "소관부처코드": "1290000",
    "id": "11",
    "법령ID": "013889",
    "공동부령정보": "",
    "시행일자": "20250101",
    "공포일자": "20241126",
    "법령약칭명": "군소음보상법 시행령"
  },
  {
    "현행연혁코드": "현행",
    "법령일련번호": "264567",
    "자법타법여부": "",
    "법령상세링크": "/DRF/lawService.do?OC=lee&target=law&MST=264567&type=HTML&mobileYn=&efYd=20240730",
    "법령명한글": "군용비행장ㆍ군사격장 소음 방지 및 피해 보상에 관한 법률 시행규칙",
    "법령구분명": "국방부령",
    "소관부처명": "국방부",
    "공포번호": "01159",
    "제개정구분명": "타법개정",
    "소관부처코드": "1290000",
    "id": "12",
    "법령ID": "013898",
    "공동부령정보": "",
    "시행일자": "20240730",
    "공포일자": "20240730",
    "법령약칭명": "군소음보상법 시행규칙"
  },
  {
    "현행연혁코드": "현행",
    "법령일련번호": "170988",
    "자법타법여부": "",
    "법령상세링크": "/DRF/lawService.do?OC=lee&target=law&MST=170988&type=HTML&mobileYn=&efYd=20150518",
    "법령명한글": "민주화운동 관련자 명예회복 및 보상 등에 관한 법률",
    "법령구분명": "법률",
    "소관부처명": "행정안전부",
    "공포번호": "13289",
    "제개정구분명": "일부개정",
    "소관부처코드": "1741000",
    "id": "13",
    "법령ID": "002028",
    "공동부령정보": "",
    "시행일자": "20150518",
    "공포일자": "20150518",
    "법령약칭명": "민주화보상법"
  },
  {
    "현행연혁코드": "현행",
    "법령일련번호": "266363",
    "자법타법여부": "",
    "법령상세링크": "/DRF/lawService.do?OC=lee&target=law&MST=266363&type=HTML&mobileYn=&efYd=20241112",
    "법령명한글": "민주화운동관련자 명예회복 및 보상 등에 관한 법률 시행령",
    "법령구분명": "대통령령",
    "소관부처명": "행정안전부",
    "공포번호": "34989",
    "제개정구분명": "타법개정",
    "소관부처코드": "1741000",
    "id": "14",
    "법령ID": "003549",
    "공동부령정보": "",
    "시행일자": "20241112",
    "공포일자": "20241112",
    "법령약칭명": "민주화보상법 시행령"
  },
  {
    "현행연혁코드": "현행",
    "법령일련번호": "241915",
    "자법타법여부": "",
    "법령상세링크": "/DRF/lawService.do?OC=lee&target=law&MST=241915&type=HTML&mobileYn=&efYd=20220727",
    "법령명한글": "부마민주항쟁 관련자의 명예회복 및 보상 등에 관한 법률",
    "법령구분명": "법률",
    "소관부처명": "행정안전부",
    "공포번호": "18845",
    "제개정구분명": "일부개정",
    "소관부처코드": "1741000",
    "id": "15",
    "법령ID": "011871",
    "공동부령정보": "",
    "시행일자": "20220727",
    "공포일자": "20220426",
    "법령약칭명": "부마항쟁보상법"
  },
  {
    "현행연혁코드": "현행",
    "법령일련번호": "266365",
    "자법타법여부": "",
    "법령상세링크": "/DRF/lawService.do?OC=lee&target=law&MST=266365&type=HTML&mobileYn=&efYd=20241112",
    "법령명한글": "부마민주항쟁 관련자의 명예회복 및 보상 등에 관한 법률 시행령",
    "법령구분명": "대통령령",
    "소관부처명": "행정안전부",
    "공포번호": "34989",
    "제개정구분명": "타법개정",
    "소관부처코드": "1741000",
    "id": "16",
    "법령ID": "011937",
    "공동부령정보": "",
    "시행일자": "20241112",
    "공포일자": "20241112",
    "법령약칭명": "부마항쟁보상법 시행령"
  },
  {
    "현행연혁코드": "현행",
    "법령일련번호": "266669",
    "자법타법여부": "",
    "법령상세링크": "/DRF/lawService.do?OC=lee&target=law&MST=266669&type=HTML&mobileYn=&efYd=20250401",
    "법령명한글": "특수임무수행자 보상에 관한 법률",
    "법령구분명": "법률",
    "소관부처명": "국방부",
    "공포번호": "20542",
    "제개정구분명": "일부개정",
    "소관부처코드": "1290000",
    "id": "17",
    "법령ID": "009618",
    "공동부령정보": "",
    "시행일자": "20250401",
    "공포일자": "20241203",
    "법령약칭명": "특임자보상법"
  },
  {
    "현행연혁코드": "현행",
    "법령일련번호": "266371",
    "자법타법여부": "",
    "법령상세링크": "/DRF/lawService.do?OC=lee&target=law&MST=266371&type=HTML&mobileYn=&efYd=20241112",
    "법령명한글": "특수임무수행자 보상에 관한 법률 시행령",
    "법령구분명": "대통령령",
    "소관부처명": "국방부",
    "공포번호": "34989",
    "제개정구분명": "타법개정",
    "소관부처코드": "1290000",
    "id": "18",
    "법령ID": "009823",
    "공동부령정보": "",
    "시행일자": "20241112",
    "공포일자": "20241112",
    "법령약칭명": "특임자보상법 시행령"
  },
  {
    "현행연혁코드": "현행",
    "법령일련번호": "257507",
    "자법타법여부": "",
    "법령상세링크": "/DRF/lawService.do?OC=lee&target=law&MST=257507&type=HTML&mobileYn=&efYd=20231229",
    "법령명한글": "형사보상 및 명예회복에 관한 법률",
    "법령구분명": "법률",
    "소관부처명": "법무부",
    "공포번호": "19857",
    "제개정구분명": "일부개정",
    "소관부처코드": "1270000",
    "id": "19",
    "법령ID": "001118",
    "공동부령정보": "",
    "시행일자": "20231229",
    "공포일자": "20231229",
    "법령약칭명": "형사보상법"
  },
  {
    "현행연혁코드": "현행",
    "법령일련번호": "117324",
    "자법타법여부": "",
    "법령상세링크": "/DRF/lawService.do?OC=lee&target=law&MST=117324&type=HTML&mobileYn=&efYd=20111124",
    "법령명한글": "형사보상 및 명예회복에 관한 법률 시행령",
    "법령구분명": "대통령령",
    "소관부처명": "법무부",
    "공포번호": "23160",
    "제개정구분명": "일부개정",
    "소관부처코드": "1270000",
    "id": "20",
    "법령ID": "005651",
    "공동부령정보": "",
    "시행일자": "20111124",
    "공포일자": "20110929",
    "법령약칭명": "형사보상법 시행령"
  }
]